setup.py
gausbin_dist/Binomialdistribution.py
gausbin_dist/Gaussiandistribution.py
gausbin_dist/Generaldistribution.py
gausbin_dist/__init__.py
gausbin_dist.egg-info/PKG-INFO
gausbin_dist.egg-info/SOURCES.txt
gausbin_dist.egg-info/dependency_links.txt
gausbin_dist.egg-info/not-zip-safe
gausbin_dist.egg-info/top_level.txt