Metadata-Version: 1.0
Name: gausbin-dist
Version: 1.0
Summary: Gaussian distributions
Home-page: UNKNOWN
Author: Lovro Vrcek
Author-email: UNKNOWN
License: UNKNOWN
Platform: UNKNOWN
